robtex_python/__init__.py
robtex_python/cli.py
robtex_python/requester.py
robtex_python/robtex_python.py
robtex_python-1.2.0.dist-info/LICENSE
robtex_python-1.2.0.dist-info/METADATA
robtex_python-1.2.0.dist-info/WHEEL
robtex_python-1.2.0.dist-info/entry_points.txt
robtex_python-1.2.0.dist-info/top_level.txt
robtex_python-1.2.0.dist-info/zip-safe
robtex_python-1.2.0.dist-info/RECORD
