Metadata-Version: 2.1
Name: robtex-python
Version: 1.2.0
Summary: Simple python wrapper for the Robtex API.
Home-page: https://github.com/fhightower/robtex-python
Author: Floyd Hightower
Author-email: UNKNOWN
License: MIT License
Keywords: robtex
Platform: UNKNOWN
Classifier: Development Status :: 4 - Beta
Classifier: Intended Audience :: Developers
Classifier: License :: OSI Approved :: MIT License
Classifier: Natural Language :: English
Classifier: Programming Language :: Python :: 3
Classifier: Programming Language :: Python :: 3.3
Classifier: Programming Language :: Python :: 3.4
Classifier: Programming Language :: Python :: 3.5
Requires-Dist: docopt (>=0.6)
Requires-Dist: requests
